etlframe/__init__.py
etlframe/nb_log_config.py
etlframe/Connections/__init__.py
etlframe/Connections/connections.py
etlframe/Connections/es.py
etlframe/Connections/sql_connections.py
etlframe/Decorator/__init__.py
etlframe/Decorator/base_decorator.py
etlframe/Decorator/decorator.py
etlframe/Error/__init__.py
etlframe/Error/error.py
etlframe/Mapping/__init__.py
etlframe/Mapping/channge_dict.py
etlframe/Mapping/dataset.py
etlframe/Mapping/heapler.py
etlframe/Mapping/mapping.py
etlframe/Reader/__init__.py
etlframe/Reader/reader.py
etlframe/Task/__init__.py
etlframe/Task/task.py
etlframe/Writer/__init__.py
etlframe/Writer/writer.py
etlframe-1.1.1.dist-info/METADATA
etlframe-1.1.1.dist-info/WHEEL
etlframe-1.1.1.dist-info/top_level.txt
etlframe-1.1.1.dist-info/RECORD
