Metadata-Version: 2.1
Name: etlframe
Version: 1.1.1
Summary: ETL框架
Home-page: 
Author: moriweiji
Author-email: moriweiji@gmail.com
License: UNKNOWN
Platform: UNKNOWN
Classifier: Development Status :: 4 - Beta
Classifier: Operating System :: OS Independent
Classifier: Intended Audience :: Developers
Classifier: License :: OSI Approved :: BSD License
Classifier: Programming Language :: Python :: 3.7
Classifier: Programming Language :: Python :: 3.8
Classifier: Programming Language :: Python :: 3.9
Requires-Dist: attrs (==21.4.0)
Requires-Dist: certifi (==2021.10.8)
Requires-Dist: cffi (==1.15.0)
Requires-Dist: charset-normalizer (==2.0.12)
Requires-Dist: click (==8.1.3)
Requires-Dist: concurrent-log-handler (==0.9.19)
Requires-Dist: cryptography (==37.0.2)
Requires-Dist: elastic-transport (==8.1.2)
Requires-Dist: elasticsearch (==8.2.0)
Requires-Dist: Flask (==2.1.2)
Requires-Dist: greenlet (==1.1.2)
Requires-Dist: idna (==3.3)
Requires-Dist: importlib-metadata (==4.11.3)
Requires-Dist: itsdangerous (==2.1.2)
Requires-Dist: Jinja2 (==3.1.2)
Requires-Dist: kafka-python (==2.0.2)
Requires-Dist: MarkupSafe (==2.1.1)
Requires-Dist: nb-filelock (==0.7)
Requires-Dist: nb-log (==7.6)
Requires-Dist: numpy (==1.21.6)
Requires-Dist: pandas (==1.1.5)
Requires-Dist: pika (==1.2.1)
Requires-Dist: portalocker (==2.4.0)
Requires-Dist: pyasn1 (==0.4.8)
Requires-Dist: pyasn1-modules (==0.2.8)
Requires-Dist: pycparser (==2.21)
Requires-Dist: pymongo (==4.0.2)
Requires-Dist: PyMySQL (==1.0.2)
Requires-Dist: python-dateutil (==2.8.2)
Requires-Dist: python-json-logger (==0.1.10)
Requires-Dist: pytz (==2022.1)
Requires-Dist: requests (==2.27.1)
Requires-Dist: service-identity (==21.1.0)
Requires-Dist: six (==1.16.0)
Requires-Dist: SQLAlchemy (==1.4.36)
Requires-Dist: tomorrow3 (==1.1.0)
Requires-Dist: typing-extensions (==4.2.0)
Requires-Dist: urllib3 (==1.26.9)
Requires-Dist: Werkzeug (==2.1.2)
Requires-Dist: zipp (==3.8.0)
